lintok/__init__.py
lintok/__main__.py
lintok/_configuration.py
lintok/_file_checking.py
lintok/_file_scanning.py
lintok/_tokenization.py
lintok/cli.py
lintok-0.0.0a6.dist-info/METADATA
lintok-0.0.0a6.dist-info/WHEEL
lintok-0.0.0a6.dist-info/entry_points.txt
lintok-0.0.0a6.dist-info/RECORD
